{
    "resourceType": "MedicationRequest",
    "id": "1008",
    "meta": {
        "versionId": "1",
        "lastUpdated": "2026-06-06T20:59:12.741+00:00",
        "tag": [
            {
                "system": "https://fhir.sk/tags",
                "code": "synthetic"
            }
        ]
    },
    "status": "active",
    "intent": "order",
    "medicationCodeableConcept": {
        "coding": [
            {
                "system": "http://www.whocc.no/atc",
                "code": "A10BA02",
                "display": "Metformin"
            }
        ],
        "text": "Metformin 500mg"
    },
    "subject": {
        "reference": "Patient/1005"
    },
    "encounter": {
        "reference": "Encounter/1007"
    },
    "authoredOn": "2026-06-06",
    "dosageInstruction": [
        {
            "text": "500mg twice daily with meals",
            "timing": {
                "repeat": {
                    "frequency": 2,
                    "period": 1,
                    "periodUnit": "d"
                }
            },
            "doseAndRate": [
                {
                    "doseQuantity": {
                        "value": 500,
                        "unit": "mg",
                        "system": "http://unitsofmeasure.org",
                        "code": "mg"
                    }
                }
            ]
        }
    ]
}
